banger/__init__.py
banger/__main__.py
banger/cli.py
banger/config.py
banger/constants.py
banger/core.py
banger/fonts.py
banger/terminal.py
banger/fonts/__init__.py
banger/fonts/api.py
banger/fonts/banner.py
banger/fonts/block.py
banger/fonts/blur.py
banger/fonts/classic.py
banger/fonts/compact.py
banger/fonts/constants.py
banger/fonts/factory.py
banger/fonts/fire.py
banger/fonts/matrix.py
banger/fonts/quadrant.py
banger/fonts/shadow.py
banger/fonts/small.py
banger/fonts/ttf.py
banger/fonts/core/__init__.py
banger/fonts/core/base.py
banger/fonts/core/character_data.py
banger/fonts/core/font_metadata.py
banger/fonts/core/interface.py
banger/fonts/core/utils.py
banger-1.1.0.dist-info/licenses/LICENSE.md
banger-1.1.0.dist-info/METADATA
banger-1.1.0.dist-info/WHEEL
banger-1.1.0.dist-info/entry_points.txt
banger-1.1.0.dist-info/top_level.txt
banger-1.1.0.dist-info/RECORD
