Metadata-Version: 2.4
Name: banger
Version: 1.1.0
Summary: Classic Unix banner command on steroids with TTF support and more.
Author-email: Marcin Orlowski <mail@marcinOrlowski.com>
License: MIT
Project-URL: Homepage, https://github.com/MarcinOrlowski/banger
Project-URL: Repository, https://github.com/MarcinOrlowski/banger
Project-URL: Issues, https://github.com/MarcinOrlowski/banger/issues
Keywords: banner,ascii,text,console
Classifier: Development Status :: 5 - Production/Stable
Classifier: Environment :: Console
Classifier: Intended Audience :: Developers
Classifier: License :: OSI Approved :: MIT License
Classifier: Operating System :: OS Independent
Classifier: Programming Language :: Python :: 3
Classifier: Programming Language :: Python :: 3.8
Classifier: Programming Language :: Python :: 3.9
Classifier: Programming Language :: Python :: 3.10
Classifier: Programming Language :: Python :: 3.11
Classifier: Programming Language :: Python :: 3.12
Classifier: Topic :: Text Processing
Classifier: Topic :: Utilities
Requires-Python: >=3.8
License-File: LICENSE.md
Requires-Dist: PyYAML>=6.0
Requires-Dist: Pillow>=8.0.0
Requires-Dist: platformdirs>=3.0.0
Provides-Extra: dev
Requires-Dist: pytest>=7.0; extra == "dev"
Requires-Dist: pytest-cov>=4.0; extra == "dev"
Requires-Dist: black>=23.0; extra == "dev"
Requires-Dist: ruff>=0.1.0; extra == "dev"
Requires-Dist: mypy>=1.0; extra == "dev"
Requires-Dist: wemake-python-styleguide; extra == "dev"
Requires-Dist: wheel; extra == "dev"
Requires-Dist: build; extra == "dev"
Requires-Dist: twine; extra == "dev"
Requires-Dist: faker; extra == "dev"
Requires-Dist: flake8; extra == "dev"
Requires-Dist: flake8-noqa; extra == "dev"
Requires-Dist: flake8-docstrings; extra == "dev"
Requires-Dist: types-Markdown; extra == "dev"
Requires-Dist: types-PyYAML; extra == "dev"
Requires-Dist: python-dateutil; extra == "dev"
Dynamic: license-file
